[{"id":1,"largeBuildingType":"주택","buildingType":"펜션(한국)","roomType":"private","isSetupForGuest":true,"maximunGuestCount":10,"bedRoomCount":5,"bedCount":5,"bedList":[{"id":1,"beds":[{"type":"퀸","count":1}]},{"id":2,"beds":[{"type":"퀸","count":1}]},{"id":3,"beds":[{"type":"퀸","count":1}]},{"id":4,"beds":[{"type":"퀸","count":1}]},{"id":5,"beds":[{"type":"퀸","count":1}]}],"publicBedList":[{"type":"소파","count":1}],"bathroomCount":5,"bathroomType":"private","country":"대한민국","city":"서울특별시","district":"마포구","streetAddress":"대흥동 ６６７","detailAddress":"","postcode":"121-080","latitude":37.5447144,"longitude":126.9429401,"amentities":["무선 인터넷","난방","에어컨","헤어 드라이어","샴푸","조식, 커피, 차","옷장/서랍장"],"conveniences":["주방","주차"],"photos":["https://jinsu-next-bnb-bucket.s3.ap-northeast-2.amazonaws.com/%EB%8B%A4%EC%9A%B4%EB%A1%9C%EB%93%9C__1f40e33b-1a99-4eb9-b1c1-b515229f11a8.jpeg","https://jinsu-next-bnb-bucket.s3.ap-northeast-2.amazonaws.com/air-bnb-headquarters-%EC%97%90%EC%96%B4%EB%B9%84%EC%95%A4%EB%B9%84_%284%29__79a9bf71-4f56-49d2-a9c1-cf6f350ef374.jpg","https://jinsu-next-bnb-bucket.s3.ap-northeast-2.amazonaws.com/PJM020719Q202_Luxe_WanakaNZ_LivingRoom_0264-LightOn_R1__7441626a-fa15-4410-bf01-f109afa3ce86.jpg"],"description":"밤하늘의 은하수가 무수히 쏟아지는 광경을 볼 수 있는 숙소입니다.\n사랑하는 연인과 특별한 추억을 만들어 보세요.","title":"밤하늘에 별을 따서 너에게 줄래.","price":113000,"startDate":"2022-02-14T00:00:00.000Z","endDate":"2022-04-02T00:00:00.000Z","hostId":1,"createdAt":"2022-02-14T10:13:58.893Z","updatedAt":"2022-02-14T10:13:58.893Z"},{"id":2,"largeBuildingType":"주택","buildingType":"펜션(한국)","roomType":"private","isSetupForGuest":true,"maximunGuestCount":10,"bedRoomCount":5,"bedCount":5,"bedList":[{"id":1,"beds":[{"type":"퀸","count":1}]},{"id":2,"beds":[{"type":"퀸","count":1}]},{"id":3,"beds":[{"type":"퀸","count":1}]},{"id":4,"beds":[{"type":"퀸","count":1}]},{"id":5,"beds":[{"type":"퀸","count":1}]}],"publicBedList":[{"type":"소파","count":1}],"bathroomCount":5,"bathroomType":"private","country":"대한민국","city":"서울특별시","district":"마포구","streetAddress":"대흥동 ６６７","detailAddress":"","postcode":"121-080","latitude":37.5447144,"longitude":126.9429401,"amentities":["무선 인터넷","난방","에어컨","헤어 드라이어","샴푸","조식, 커피, 차","옷장/서랍장"],"conveniences":["주방","주차"],"photos":["https://jinsu-next-bnb-bucket.s3.ap-northeast-2.amazonaws.com/%EB%8B%A4%EC%9A%B4%EB%A1%9C%EB%93%9C__1f40e33b-1a99-4eb9-b1c1-b515229f11a8.jpeg","https://jinsu-next-bnb-bucket.s3.ap-northeast-2.amazonaws.com/air-bnb-headquarters-%EC%97%90%EC%96%B4%EB%B9%84%EC%95%A4%EB%B9%84_%284%29__79a9bf71-4f56-49d2-a9c1-cf6f350ef374.jpg","https://jinsu-next-bnb-bucket.s3.ap-northeast-2.amazonaws.com/PJM020719Q202_Luxe_WanakaNZ_LivingRoom_0264-LightOn_R1__7441626a-fa15-4410-bf01-f109afa3ce86.jpg"],"description":"밤하늘의 은하수가 무수히 쏟아지는 광경을 볼 수 있는 숙소입니다.\n사랑하는 연인과 특별한 추억을 만들어 보세요.","title":"밤하늘에 별을 따서 너에게 줄래.","price":113000,"startDate":"2022-02-14T00:00:00.000Z","endDate":"2022-04-02T00:00:00.000Z","hostId":1,"createdAt":"2022-02-14T10:14:46.621Z","updatedAt":"2022-02-14T10:14:46.621Z"},{"id":3,"largeBuildingType":"주택","buildingType":"펜션(한국)","roomType":"private","isSetupForGuest":true,"maximunGuestCount":10,"bedRoomCount":5,"bedCount":5,"bedList":[{"id":1,"beds":[{"type":"퀸","count":1}]},{"id":2,"beds":[{"type":"퀸","count":1}]},{"id":3,"beds":[{"type":"퀸","count":1}]},{"id":4,"beds":[{"type":"퀸","count":1}]},{"id":5,"beds":[{"type":"퀸","count":1}]}],"publicBedList":[{"type":"소파","count":1}],"bathroomCount":5,"bathroomType":"private","country":"대한민국","city":"서울특별시","district":"마포구","streetAddress":"대흥동 ６６７","detailAddress":"","postcode":"121-080","latitude":37.5447144,"longitude":126.9429401,"amentities":["무선 인터넷","난방","에어컨","헤어 드라이어","샴푸","조식, 커피, 차","옷장/서랍장"],"conveniences":["주방","주차"],"photos":["https://jinsu-next-bnb-bucket.s3.ap-northeast-2.amazonaws.com/%EB%8B%A4%EC%9A%B4%EB%A1%9C%EB%93%9C__1f40e33b-1a99-4eb9-b1c1-b515229f11a8.jpeg","https://jinsu-next-bnb-bucket.s3.ap-northeast-2.amazonaws.com/air-bnb-headquarters-%EC%97%90%EC%96%B4%EB%B9%84%EC%95%A4%EB%B9%84_%284%29__79a9bf71-4f56-49d2-a9c1-cf6f350ef374.jpg","https://jinsu-next-bnb-bucket.s3.ap-northeast-2.amazonaws.com/PJM020719Q202_Luxe_WanakaNZ_LivingRoom_0264-LightOn_R1__7441626a-fa15-4410-bf01-f109afa3ce86.jpg"],"description":"밤하늘의 은하수가 무수히 쏟아지는 광경을 볼 수 있는 숙소입니다.\n사랑하는 연인과 특별한 추억을 만들어 보세요.","title":"밤하늘에 별을 따서 너에게 줄래.","price":113000,"startDate":"2022-02-14T00:00:00.000Z","endDate":"2022-04-02T00:00:00.000Z","hostId":1,"createdAt":"2022-02-14T10:15:57.404Z","updatedAt":"2022-02-14T10:15:57.404Z"},{"id":4,"largeBuildingType":"주택","buildingType":"주택","roomType":"entire","isSetupForGuest":true,"maximunGuestCount":1,"bedRoomCount":1,"bedCount":1,"bedList":[{"id":1,"beds":[]}],"publicBedList":[],"bathroomCount":1,"bathroomType":"private","country":"대한민국","city":"서울특별시","district":"마포구","streetAddress":"대흥동 ６６７","detailAddress":"","postcode":"121-080","latitude":37.5447144,"longitude":126.9429401,"amentities":["무선 인터넷"],"conveniences":[],"photos":["https://jinsu-next-bnb-bucket.s3.ap-northeast-2.amazonaws.com/%EB%8B%A4%EC%9A%B4%EB%A1%9C%EB%93%9C%20%281%29__759ef2fb-9c68-4241-adc7-63c205d80638.jpeg"],"description":"dwdwqdw","title":"qdqwdd","price":3212321,"startDate":"2022-02-14T00:00:00.000Z","endDate":"2022-03-10T00:00:00.000Z","hostId":1,"createdAt":"2022-02-14T10:26:49.714Z","updatedAt":"2022-02-14T10:26:49.714Z"},{"id":5,"largeBuildingType":"주택","buildingType":"주택","roomType":"entire","isSetupForGuest":true,"maximunGuestCount":1,"bedRoomCount":1,"bedCount":1,"bedList":[{"id":1,"beds":[]}],"publicBedList":[],"bathroomCount":1,"bathroomType":"private","country":"대한민국","city":"서울특별시","district":"마포구","streetAddress":"대흥동 ６６７","detailAddress":"","postcode":"121-080","latitude":37.5447144,"longitude":126.9429401,"amentities":["무선 인터넷"],"conveniences":[],"photos":["https://jinsu-next-bnb-bucket.s3.ap-northeast-2.amazonaws.com/%EB%8B%A4%EC%9A%B4%EB%A1%9C%EB%93%9C%20%281%29__759ef2fb-9c68-4241-adc7-63c205d80638.jpeg"],"description":"dwdwqdw","title":"qdqwdd","price":3212321,"startDate":"2022-02-14T00:00:00.000Z","endDate":"2022-03-10T00:00:00.000Z","hostId":1,"createdAt":"2022-02-14T10:28:14.479Z","updatedAt":"2022-02-14T10:28:14.479Z"},{"id":6,"largeBuildingType":"주택","buildingType":"주택","roomType":"entire","isSetupForGuest":true,"maximunGuestCount":1,"bedRoomCount":1,"bedCount":1,"bedList":[{"id":1,"beds":[]}],"publicBedList":[],"bathroomCount":1,"bathroomType":"private","country":"대한민국","city":"서울특별시","district":"마포구","streetAddress":"대흥동 ６６７","detailAddress":"","postcode":"121-080","latitude":37.5447144,"longitude":126.9429401,"amentities":["무선 인터넷"],"conveniences":[],"photos":["https://jinsu-next-bnb-bucket.s3.ap-northeast-2.amazonaws.com/%EB%8B%A4%EC%9A%B4%EB%A1%9C%EB%93%9C%20%281%29__759ef2fb-9c68-4241-adc7-63c205d80638.jpeg"],"description":"dwdwqdw","title":"qdqwdd","price":3212321,"startDate":"2022-02-14T00:00:00.000Z","endDate":"2022-03-10T00:00:00.000Z","hostId":1,"createdAt":"2022-02-14T10:29:05.406Z","updatedAt":"2022-02-14T10:29:05.406Z"},{"id":7,"largeBuildingType":"아파트","buildingType":"아파트","roomType":"entire","isSetupForGuest":false,"maximunGuestCount":1,"bedRoomCount":1,"bedCount":1,"bedList":[{"id":1,"beds":[{"type":"유아 침대","count":1}]}],"publicBedList":[],"bathroomCount":1,"bathroomType":"private","country":"대한민국","city":"서울특별시","district":"마포구","streetAddress":"대흥동 ６６７","detailAddress":"","postcode":"121-080","latitude":37.5447144,"longitude":126.9429401,"amentities":["무선 인터넷"],"conveniences":["헬스장"],"photos":["https://jinsu-next-bnb-bucket.s3.ap-northeast-2.amazonaws.com/PJM020719Q202_Luxe_WanakaNZ_LivingRoom_0264-LightOn_R1__92741fea-f4f7-45b0-9846-87a6fc812d4b.jpg"],"description":"dqwdwdw","title":"dwqdwqdwqdw","price":321321321312,"startDate":"2022-02-15T00:00:00.000Z","endDate":"2022-02-24T00:00:00.000Z","hostId":1,"createdAt":"2022-02-14T10:30:54.278Z","updatedAt":"2022-02-14T10:30:54.278Z"},{"id":8,"largeBuildingType":"아파트","buildingType":"아파트","roomType":"entire","isSetupForGuest":false,"maximunGuestCount":1,"bedRoomCount":1,"bedCount":1,"bedList":[{"id":1,"beds":[{"type":"유아 침대","count":1}]}],"publicBedList":[],"bathroomCount":1,"bathroomType":"private","country":"대한민국","city":"서울특별시","district":"마포구","streetAddress":"대흥동 ６６７","detailAddress":"","postcode":"121-080","latitude":37.5447144,"longitude":126.9429401,"amentities":["무선 인터넷"],"conveniences":["헬스장"],"photos":["https://jinsu-next-bnb-bucket.s3.ap-northeast-2.amazonaws.com/PJM020719Q202_Luxe_WanakaNZ_LivingRoom_0264-LightOn_R1__92741fea-f4f7-45b0-9846-87a6fc812d4b.jpg"],"description":"dqwdwdw","title":"dwqdwqdwqdw","price":321321321312,"startDate":"2022-02-15T00:00:00.000Z","endDate":"2022-02-24T00:00:00.000Z","hostId":1,"createdAt":"2022-02-14T10:33:43.443Z","updatedAt":"2022-02-14T10:33:43.443Z"},{"id":9,"largeBuildingType":"주택","buildingType":"펜션(한국)","roomType":"entire","isSetupForGuest":true,"maximunGuestCount":6,"bedRoomCount":1,"bedCount":2,"bedList":[{"id":1,"beds":[{"type":"퀸","count":1},{"type":"싱글","count":1},{"type":"에어 매트릭스","count":1}]}],"publicBedList":[],"bathroomCount":1,"bathroomType":"private","country":"대한민국","city":"서울특별시","district":"마포구","streetAddress":"대흥동 ６６７","detailAddress":"","postcode":"121-080","latitude":37.5447144,"longitude":126.9429401,"amentities":["무선 인터넷","난방","에어컨","헤어 드라이어","조식, 커피, 차","옷장/서랍장","게스트 전용 출입문"],"conveniences":["주방","주차"],"photos":["https://jinsu-next-bnb-bucket.s3.ap-northeast-2.amazonaws.com/Airbnb_Georgia3__3fcd8491-76dd-4f7d-90f2-9575cc604682.jpg"],"description":"greegrgr","title":"wdwqddwdwdw","price":323212,"startDate":"2022-02-14T00:00:00.000Z","endDate":"2022-02-17T00:00:00.000Z","hostId":1,"createdAt":"2022-02-14T10:38:10.873Z","updatedAt":"2022-02-14T10:38:10.873Z"},{"id":10,"largeBuildingType":"주택","buildingType":"주택","roomType":"entire","isSetupForGuest":true,"maximunGuestCount":6,"bedRoomCount":1,"bedCount":2,"bedList":[{"id":1,"beds":[{"type":"퀸","count":1},{"type":"싱글","count":1},{"type":"에어 매트릭스","count":1}]}],"publicBedList":[],"bathroomCount":1,"bathroomType":"private","country":"대한민국","city":"서울특별시","district":"마포구","streetAddress":"대흥동 ６６７","detailAddress":"","postcode":"121-080","latitude":37.5447144,"longitude":126.9429401,"amentities":["무선 인터넷","난방","에어컨","헤어 드라이어","조식, 커피, 차","옷장/서랍장","게스트 전용 출입문"],"conveniences":["주방","주차"],"photos":["https://jinsu-next-bnb-bucket.s3.ap-northeast-2.amazonaws.com/Airbnb_Georgia3__3fcd8491-76dd-4f7d-90f2-9575cc604682.jpg"],"description":"greegrgr","title":"wdwqddwdwdw","price":323212,"startDate":"2022-02-14T00:00:00.000Z","endDate":"2022-02-17T00:00:00.000Z","hostId":1,"createdAt":"2022-02-14T10:39:40.222Z","updatedAt":"2022-02-14T10:39:40.222Z"},{"id":11,"largeBuildingType":"주택","buildingType":"주택","roomType":"entire","isSetupForGuest":true,"maximunGuestCount":6,"bedRoomCount":1,"bedCount":2,"bedList":[{"id":1,"beds":[{"type":"퀸","count":1},{"type":"싱글","count":1},{"type":"에어 매트릭스","count":1}]}],"publicBedList":[],"bathroomCount":1,"bathroomType":"private","country":"대한민국","city":"서울특별시","district":"마포구","streetAddress":"대흥동 ６６７","detailAddress":"","postcode":"121-080","latitude":37.5447144,"longitude":126.9429401,"amentities":["무선 인터넷","난방","에어컨","헤어 드라이어","조식, 커피, 차","옷장/서랍장","게스트 전용 출입문"],"conveniences":["주방","주차"],"photos":["https://jinsu-next-bnb-bucket.s3.ap-northeast-2.amazonaws.com/Airbnb_Georgia3__3fcd8491-76dd-4f7d-90f2-9575cc604682.jpg"],"description":"greegrgr","title":"wdwqddwdwdw","price":323212,"startDate":"2022-02-14T00:00:00.000Z","endDate":"2022-02-17T00:00:00.000Z","hostId":1,"createdAt":"2022-02-14T10:41:31.588Z","updatedAt":"2022-02-14T10:41:31.588Z"},{"id":12,"largeBuildingType":"주택","buildingType":"주택","roomType":"entire","isSetupForGuest":true,"maximunGuestCount":6,"bedRoomCount":1,"bedCount":2,"bedList":[{"id":1,"beds":[{"type":"퀸","count":1},{"type":"싱글","count":1},{"type":"에어 매트릭스","count":1}]}],"publicBedList":[],"bathroomCount":1,"bathroomType":"private","country":"대한민국","city":"서울특별시","district":"마포구","streetAddress":"대흥동 ６６７","detailAddress":"","postcode":"121-080","latitude":37.5447144,"longitude":126.9429401,"amentities":["무선 인터넷","난방","에어컨","헤어 드라이어","조식, 커피, 차","옷장/서랍장","게스트 전용 출입문"],"conveniences":["주방","주차"],"photos":["https://jinsu-next-bnb-bucket.s3.ap-northeast-2.amazonaws.com/Airbnb_Georgia3__3fcd8491-76dd-4f7d-90f2-9575cc604682.jpg"],"description":"greegrgr","title":"wdwqddwdwdw","price":323212,"startDate":"2022-02-14T00:00:00.000Z","endDate":"2022-02-17T00:00:00.000Z","hostId":1,"createdAt":"2022-02-14T10:42:35.590Z","updatedAt":"2022-02-14T10:42:35.590Z"},{"id":13,"largeBuildingType":"아파트","buildingType":"공동주택","roomType":"entire","isSetupForGuest":true,"maximumGuestCount":1,"bedRoomCount":1,"bedCount":1,"bedList":[{"id":1,"beds":[{"type":"해먹","count":1}]}],"publicBedList":[],"bathroomCount":1,"bathroomType":"private","country":"대한민국","city":"서울특별시","district":"마포구","streetAddress":"대흥동 ６６７","detailAddress":"","postcode":"121-080","latitude":37.5447144,"longitude":126.9429401,"amentities":["에어컨"],"conveniences":[],"photos":["https://jinsu-next-bnb-bucket.s3.ap-northeast-2.amazonaws.com/PJM020719Q202_Luxe_WanakaNZ_LivingRoom_0264-LightOn_R1__97d6f9af-e1fd-4d13-b306-01fe1a18e136.jpg"],"description":"dwqdwdw","title":"dwqdd","price":321312,"startDate":"2022-02-15T00:00:00.000Z","endDate":"2022-02-26T00:00:00.000Z","hostId":1,"createdAt":"2022-02-14T10:47:52.247Z","updatedAt":"2022-02-14T10:47:52.247Z"},{"id":14,"largeBuildingType":"아파트","buildingType":"공동주택","roomType":"entire","isSetupForGuest":true,"maximumGuestCount":1,"bedRoomCount":1,"bedCount":1,"bedList":[{"id":1,"beds":[{"type":"해먹","count":1}]}],"publicBedList":[],"bathroomCount":1,"bathroomType":"private","country":"대한민국","city":"서울특별시","district":"마포구","streetAddress":"대흥동 ６６７","detailAddress":"","postcode":"121-080","latitude":37.5447144,"longitude":126.9429401,"amentities":["에어컨"],"conveniences":[],"photos":["https://jinsu-next-bnb-bucket.s3.ap-northeast-2.amazonaws.com/PJM020719Q202_Luxe_WanakaNZ_LivingRoom_0264-LightOn_R1__97d6f9af-e1fd-4d13-b306-01fe1a18e136.jpg"],"description":"dwqdwdw","title":"dwqdd","price":321312,"startDate":"2022-02-15T00:00:00.000Z","endDate":"2022-02-26T00:00:00.000Z","hostId":1,"createdAt":"2022-02-14T10:49:50.141Z","updatedAt":"2022-02-14T10:49:50.141Z"},{"id":15,"largeBuildingType":"아파트","buildingType":"아파트","roomType":"entire","isSetupForGuest":true,"maximumGuestCount":1,"bedRoomCount":1,"bedCount":1,"bedList":[{"id":1,"beds":[{"type":"해먹","count":1}]}],"publicBedList":[],"bathroomCount":1,"bathroomType":"private","country":"대한민국","city":"서울특별시","district":"마포구","streetAddress":"대흥동 ６６７","detailAddress":"","postcode":"121-080","latitude":37.5447144,"longitude":126.9429401,"amentities":["에어컨"],"conveniences":[],"photos":["https://jinsu-next-bnb-bucket.s3.ap-northeast-2.amazonaws.com/PJM020719Q202_Luxe_WanakaNZ_LivingRoom_0264-LightOn_R1__97d6f9af-e1fd-4d13-b306-01fe1a18e136.jpg"],"description":"dwqdwdw","title":"dwqdd","price":321312,"startDate":"2022-02-15T00:00:00.000Z","endDate":"2022-02-26T00:00:00.000Z","hostId":1,"createdAt":"2022-02-14T10:50:22.031Z","updatedAt":"2022-02-14T10:50:22.032Z"},{"id":16,"largeBuildingType":"주택","buildingType":"통나무집","roomType":"entire","isSetupForGuest":true,"maximumGuestCount":3,"bedRoomCount":1,"bedCount":1,"bedList":[{"id":1,"beds":[{"type":"퀸","count":1}]}],"publicBedList":[{"type":"소파","count":1}],"bathroomCount":1,"bathroomType":"private","country":"대한민국","city":"서울특별시","district":"마포구","streetAddress":"대흥동 ２１６−２","detailAddress":"","postcode":"121-080","latitude":37.5482241,"longitude":126.9416559,"amentities":["무선 인터넷","난방","에어컨","헤어 드라이어","업무가능 공간/책상"],"conveniences":["주방","주차"],"photos":["https://jinsu-next-bnb-bucket.s3.amazonaws.com/Airbnb_Texas__88b2ce7d-ca7f-46c1-b51f-cf0de92e8f77.jpg"],"description":"서울 유명 도시 홍대, 신촌 과 근접","title":"밤하늘의 별을 따서 너에게 줄래","price":70000,"startDate":"2022-02-20T00:00:00.000Z","endDate":"2022-04-02T00:00:00.000Z","hostId":1,"createdAt":"2022-02-20T08:13:53.173Z","updatedAt":"2022-02-20T08:13:53.173Z"},{"id":17,"largeBuildingType":"아파트","buildingType":"아파트","roomType":"entire","isSetupForGuest":true,"maximumGuestCount":1,"bedRoomCount":1,"bedCount":1,"bedList":[{"id":1,"beds":[{"type":"소파","count":1}]}],"publicBedList":[],"bathroomCount":1,"bathroomType":"private","country":"대한민국","city":"서울특별시","district":"마포구","streetAddress":"대흥동 ６７２−２","detailAddress":"","postcode":"121-080","latitude":37.5448591,"longitude":126.9429019,"amentities":["무선 인터넷","에어컨","난방","헤어 드라이어","업무가능 공간/책상"],"conveniences":["주방"],"photos":["https://jinsu-next-bnb-bucket.s3.ap-northeast-2.amazonaws.com/2459fa90-5f66-4198-a8f2-43d8f8783bc2__c6fe5af7-73cc-47f0-8dcc-62c5ea208bb8.jpg","https://jinsu-next-bnb-bucket.s3.ap-northeast-2.amazonaws.com/%EB%8B%A4%EC%9A%B4%EB%A1%9C%EB%93%9C__94bc6f37-23c0-4d5d-9f1a-948087a7f149.jpeg","https://jinsu-next-bnb-bucket.s3.ap-northeast-2.amazonaws.com/air-bnb-headquarters-%EC%97%90%EC%96%B4%EB%B9%84%EC%95%A4%EB%B9%84_%284%29__0192c441-87a1-4349-b160-1d09b512347e.jpg","https://jinsu-next-bnb-bucket.s3.ap-northeast-2.amazonaws.com/images%20%281%29__025afdcf-32ff-4f94-91bd-8a2f409e727e.jpeg","https://jinsu-next-bnb-bucket.s3.ap-northeast-2.amazonaws.com/Airbnb_Texas__398c8cf3-51ca-486e-8e0a-3cb92236ae4d.jpg"],"description":"밤하늘의 별을 보고 싶나요?\n","title":"밤하늘의 별을 따서 너에게 줄래. 너는 내가 사랑하니까 더 소중하니까","price":110000,"startDate":"2022-02-20T18:00:00.000Z","endDate":"2022-03-25T00:00:00.000Z","hostId":1,"createdAt":"2022-02-20T13:08:19.406Z","updatedAt":"2022-02-20T13:08:19.406Z"}]